{
  "fixed": [
    {
      "id": "pliers",
      "name": "pliers",
      "availableItems": [
        {
          "in": "rope",
          "out": "short-rope"
        },
        {
          "in": "necklace",
          "out": "gem"
        },
        {
          "in": "umbrella",
          "out": "umbrella-stand"
        },
        {
          "in": "wine-bottle",
          "out": "broken-wine-bottle"
        }
      ]
    },
    {
      "id": "table",
      "name": "table",
      "availableItems": [
        {
          "in": "rope",
          "out": "repo-ladder"
        },
        {
          "in": "umbrella",
          "out": "umbrella-stand"
        },
        {
          "in": "wine-bottle",
          "out": "clean-table"
        }
      ]
    },
    {
      "id": "clean-table",
      "name": "clean table",
      "availableItems": []
    },
    {
      "id": "fake-door",
      "name": "fake door",
      "availableItems": []
    },
    {
      "id": "groove",
      "name": "groove",
      "availableItems": [
        {
          "in": "gem",
          "out": "groove-diamond"
        }
      ]
    },
    {
      "id": "groove-diamond",
      "name": "groove diamond",
      "availableItems": []
    },
    {
      "id": "curtain",
      "name": "curtain",
      "availableItems": [
        {
          "in": "gem",
          "out": "clean-gem"
        }
      ]
    },
    {
      "id": "reflection",
      "name": "reflection",
      "availableItems": [
        {
          "in": "clean-gem",
          "out": "open-exit"
        }
      ]
    },
    {
      "id": "exit",
      "name": "exit",
      "availableItems": []
    },
    {
      "id": "little-monster",
      "name": "little monster",
      "availableItems": [
        {
          "in": "umbrella",
          "out": "little-monster-umbrella"
        }
      ]
    },
    {
      "id": "little-monster-umbrella",
      "name": "little monster umbrella",
      "availableItems": []
    }
  ],
  "portable": [
    {
      "id": "rope",
      "name": "rope"
    },
    {
      "id": "short-rope",
      "name": "short rope"
    },
    {
      "id": "ladder",
      "name": "ladder"
    },
    {
      "id": "necklace",
      "name": "necklace"
    },
    {
      "id": "wine-bottle",
      "name": "wine bottle"
    },
    {
      "id": "broken-wine-bottle",
      "name": "broken wine bottle"
    },
    {
      "id": "clean-gem",
      "name": "clean gem"
    },
    {
      "id": "gem",
      "name": "gem"
    },
    {
      "id": "umbrella",
      "name": "umbrella"
    },
    {
      "id": "umbrella-stand",
      "name": "umbrella stand"
    },
    {
      "id": "umbrella-cloth",
      "name": "umbrella cloth"
    }
  ]
}
